{
    "header": {
        "metadata": [
            {
                "metaName": "adskFileFormatVersion",
                "metaValue": "100L"
            }
        ]
    },
    "namespaces": [],
    "types": [],
    "compounds": [
        {
            "name": "hiddenStrings::latticeWithSmooth",
            "metadata": [
                {
                    "metaName": "io_nodes",
                    "metadata": [
                        {
                            "metaName": "io_inodes",
                            "metadata": [
                                {
                                    "metaName": "input",
                                    "metadata": [
                                        {
                                            "metaName": "DisplayMode",
                                            "metaType": "string",
                                            "metaValue": "2"
                                        },
                                        {
                                            "metaName": "io_ports",
                                            "metadata": [
                                                {
                                                    "metaName": "latticeShape"
                                                },
                                                {
                                                    "metaName": "geometryShape"
                                                },
                                                {
                                                    "metaName": "latticeBase"
                                                },
                                                {
                                                    "metaName": "smoothIterations"
                                                }
                                            ]
                                        },
                                        {
                                            "metaName": "LayoutPos",
                                            "metaType": "string",
                                            "metaValue": "-1386 -846"
                                        }
                                    ]
                                }
                            ]
                        },
                        {
                            "metaName": "io_onodes",
                            "metadata": [
                                {
                                    "metaName": "output",
                                    "metadata": [
                                        {
                                            "metaName": "DisplayMode",
                                            "metaType": "string",
                                            "metaValue": "2"
                                        },
                                        {
                                            "metaName": "LayoutPos",
                                            "metaType": "string",
                                            "metaValue": "-210.087 -874.78"
                                        },
                                        {
                                            "metaName": "io_ports",
                                            "metadata": [
                                                {
                                                    "metaName": "out_geometry"
                                                }
                                            ]
                                        }
                                    ]
                                }
                            ]
                        }
                    ]
                },
                {
                    "metaName": "_recentNode_",
                    "metaType": "string",
                    "metaValue": "BifrostGraph,Core::Iterators,iterate"
                },
                {
                    "metaName": "_recentNode_",
                    "metaType": "string",
                    "metaValue": "BifrostGraph,Geometry::Properties,set_point_position"
                },
                {
                    "metaName": "_recentNode_",
                    "metaType": "string",
                    "metaValue": "BifrostGraph,Geometry::Properties,get_point_position"
                },
                {
                    "metaName": "_recentNode_",
                    "metaType": "string",
                    "metaValue": "BifrostGraph,Core::Iterators,for_each"
                },
                {
                    "metaName": "_recentNode_",
                    "metaType": "string",
                    "metaValue": "BifrostGraph,rigging,get_adjacent_vertex"
                },
                {
                    "metaName": "ViewportRect",
                    "metaType": "string",
                    "metaValue": "-1482 -1227.5 1602 946"
                },
                {
                    "metaName": "compoundIsGraph",
                    "metaValue": "true"
                },
                {
                    "metaName": "category",
                    "metaType": "string",
                    "metaValue": "hiddenStrings"
                }
            ],
            "ports": [
                {
                    "portName": "latticeShape",
                    "portDirection": "input",
                    "portType": "Object",
                    "portDefault": {}
                },
                {
                    "portName": "geometryShape",
                    "portDirection": "input",
                    "portType": "Object",
                    "portDefault": {}
                },
                {
                    "portName": "latticeBase",
                    "portDirection": "input",
                    "portType": "Object",
                    "portDefault": {}
                },
                {
                    "portName": "out_geometry",
                    "portDirection": "output",
                    "portType": "Object"
                },
                {
                    "portName": "smoothIterations",
                    "portDirection": "input",
                    "portType": "long",
                    "portDefault": "5"
                }
            ],
            "compounds": [
                {
                    "name": "lattice_compound",
                    "uriImported": "stream:/latticeWithSmoothShape",
                    "metadata": [
                        {
                            "metaName": "io_nodes",
                            "metadata": [
                                {
                                    "metaName": "io_inodes",
                                    "metadata": [
                                        {
                                            "metaName": "input",
                                            "metadata": [
                                                {
                                                    "metaName": "DisplayMode",
                                                    "metaType": "string",
                                                    "metaValue": "2"
                                                },
                                                {
                                                    "metaName": "LayoutPos",
                                                    "metaType": "string",
                                                    "metaValue": "-1160.5 -809.205"
                                                },
                                                {
                                                    "metaName": "io_ports",
                                                    "metadata": [
                                                        {
                                                            "metaName": "latticeBase"
                                                        },
                                                        {
                                                            "metaName": "geometryShape"
                                                        },
                                                        {
                                                            "metaName": "latticeShape"
                                                        },
                                                        {
                                                            "metaName": "smoothIterations"
                                                        }
                                                    ]
                                                }
                                            ]
                                        }
                                    ]
                                },
                                {
                                    "metaName": "io_onodes",
                                    "metadata": [
                                        {
                                            "metaName": "output",
                                            "metadata": [
                                                {
                                                    "metaName": "DisplayMode",
                                                    "metaType": "string",
                                                    "metaValue": "2"
                                                },
                                                {
                                                    "metaName": "io_ports",
                                                    "metadata": [
                                                        {
                                                            "metaName": "out_geometry"
                                                        }
                                                    ]
                                                },
                                                {
                                                    "metaName": "LayoutPos",
                                                    "metaType": "string",
                                                    "metaValue": "2494.98 -1221.59"
                                                }
                                            ]
                                        }
                                    ]
                                }
                            ]
                        },
                        {
                            "metaName": "backdrop",
                            "metadata": [
                                {
                                    "metaName": "type",
                                    "metaType": "string",
                                    "metaValue": "backdrop"
                                },
                                {
                                    "metaName": "coords",
                                    "metaType": "string",
                                    "metaValue": "984.097 -1621.9 1239.27 656.91"
                                },
                                {
                                    "metaName": "text",
                                    "metaType": "string",
                                    "metaValue": "SMOOTH\n"
                                }
                            ]
                        },
                        {
                            "metaName": "backdrop1",
                            "metadata": [
                                {
                                    "metaName": "type",
                                    "metaType": "string",
                                    "metaValue": "backdrop"
                                },
                                {
                                    "metaName": "text",
                                    "metaType": "string",
                                    "metaValue": "WRAP\n"
                                },
                                {
                                    "metaName": "coords",
                                    "metaType": "string",
                                    "metaValue": "-873.112 -1630.5 1752.85 1100.29"
                                }
                            ]
                        },
                        {
                            "metaName": "ViewportRect",
                            "metaType": "string",
                            "metaValue": "-821.962 -1836.27 2965.36 1751.08"
                        },
                        {
                            "metaName": "_recentNode_",
                            "metaType": "string",
                            "metaValue": "BifrostGraph,Core::Math,rotate_by_quaternion"
                        },
                        {
                            "metaName": "_recentNode_",
                            "metaType": "string",
                            "metaValue": "BifrostGraph,Geometry::Properties,set_point_position"
                        },
                        {
                            "metaName": "_recentNode_",
                            "metaType": "string",
                            "metaValue": "BifrostGraph,Geometry::Properties,get_point_position"
                        },
                        {
                            "metaName": "_recentNode_",
                            "metaType": "string",
                            "metaValue": "BifrostGraph,Core::Math,add"
                        },
                        {
                            "metaName": "_recentNode_",
                            "metaType": "string",
                            "metaValue": "BifrostGraph,Core::Math,subtract"
                        }
                    ],
                    "ports": [
                        {
                            "portName": "latticeBase",
                            "portDirection": "input",
                            "portType": "Object"
                        },
                        {
                            "portName": "geometryShape",
                            "portDirection": "input",
                            "portType": "Object"
                        },
                        {
                            "portName": "latticeShape",
                            "portDirection": "input",
                            "portType": "Object"
                        },
                        {
                            "portName": "out_geometry",
                            "portDirection": "output",
                            "portType": "Object"
                        },
                        {
                            "portName": "smoothIterations",
                            "portDirection": "input",
                            "portType": "long"
                        }
                    ],
                    "compoundNodes": [
                        {
                            "nodeName": "add",
                            "nodeType": "Core::Math::add",
                            "multiInPortNames": [
                                "output1",
                                "sampled_data"
                            ],
                            "metadata": [
                                {
                                    "metaName": "DisplayMode",
                                    "metaType": "string",
                                    "metaValue": "2"
                                },
                                {
                                    "metaName": "LayoutPos",
                                    "metaType": "string",
                                    "metaValue": "558 -878"
                                }
                            ]
                        },
                        {
                            "nodeName": "get_closest_locations",
                            "nodeType": "Geometry::Query::get_closest_locations",
                            "metadata": [
                                {
                                    "metaName": "DisplayMode",
                                    "metaType": "string",
                                    "metaValue": "2"
                                },
                                {
                                    "metaName": "LayoutPos",
                                    "metaType": "string",
                                    "metaValue": "-552 -1299"
                                }
                            ]
                        },
                        {
                            "nodeName": "get_point_position",
                            "nodeType": "Geometry::Properties::get_point_position",
                            "metadata": [
                                {
                                    "metaName": "DisplayMode",
                                    "metaType": "string",
                                    "metaValue": "2"
                                },
                                {
                                    "metaName": "LayoutPos",
                                    "metaType": "string",
                                    "metaValue": "-852 -1479"
                                }
                            ]
                        },
                        {
                            "nodeName": "sample_property",
                            "nodeType": "Geometry::Query::sample_property",
                            "metadata": [
                                {
                                    "metaName": "DisplayMode",
                                    "metaType": "string",
                                    "metaValue": "2"
                                },
                                {
                                    "metaName": "LayoutPos",
                                    "metaType": "string",
                                    "metaValue": "-222 -1179"
                                }
                            ]
                        },
                        {
                            "nodeName": "sample_property1",
                            "nodeType": "Geometry::Query::sample_property",
                            "metadata": [
                                {
                                    "metaName": "DisplayMode",
                                    "metaType": "string",
                                    "metaValue": "2"
                                },
                                {
                                    "metaName": "LayoutPos",
                                    "metaType": "string",
                                    "metaValue": "-222 -849"
                                }
                            ]
                        },
                        {
                            "nodeName": "subtract",
                            "nodeType": "Core::Math::subtract",
                            "multiInPortNames": [
                                "point_position",
                                "sampled_data"
                            ],
                            "metadata": [
                                {
                                    "metaName": "DisplayMode",
                                    "metaType": "string",
                                    "metaValue": "2"
                                },
                                {
                                    "metaName": "LayoutPos",
                                    "metaType": "string",
                                    "metaValue": "108 -1598"
                                }
                            ]
                        },
                        {
                            "nodeName": "smooth_mesh_compound",
                            "nodeType": "rigging::smooth_mesh_compound",
                            "metadata": [
                                {
                                    "metaName": "DisplayMode",
                                    "metaType": "string",
                                    "metaValue": "2"
                                },
                                {
                                    "metaName": "LayoutPos",
                                    "metaType": "string",
                                    "metaValue": "1308 -1509"
                                }
                            ]
                        },
                        {
                            "nodeName": "subtract1",
                            "nodeType": "Core::Math::subtract",
                            "multiInPortNames": [
                                "output1",
                                "point_position"
                            ],
                            "metadata": [
                                {
                                    "metaName": "DisplayMode",
                                    "metaType": "string",
                                    "metaValue": "2"
                                },
                                {
                                    "metaName": "LayoutPos",
                                    "metaType": "string",
                                    "metaValue": "1038 -1238"
                                }
                            ]
                        },
                        {
                            "nodeName": "set_point_position1",
                            "nodeType": "Geometry::Properties::set_point_position",
                            "metadata": [
                                {
                                    "metaName": "DisplayMode",
                                    "metaType": "string",
                                    "metaValue": "2"
                                },
                                {
                                    "metaName": "LayoutPos",
                                    "metaType": "string",
                                    "metaValue": "1038 -1598"
                                }
                            ]
                        },
                        {
                            "nodeName": "add1",
                            "nodeType": "Core::Math::add",
                            "multiInPortNames": [
                                "point_position",
                                "point_position1"
                            ],
                            "metadata": [
                                {
                                    "metaName": "DisplayMode",
                                    "metaType": "string",
                                    "metaValue": "2"
                                },
                                {
                                    "metaName": "LayoutPos",
                                    "metaType": "string",
                                    "metaValue": "1638 -1328"
                                }
                            ]
                        },
                        {
                            "nodeName": "get_point_position1",
                            "nodeType": "Geometry::Properties::get_point_position",
                            "metadata": [
                                {
                                    "metaName": "DisplayMode",
                                    "metaType": "string",
                                    "metaValue": "2"
                                },
                                {
                                    "metaName": "LayoutPos",
                                    "metaType": "string",
                                    "metaValue": "1638 -1509"
                                }
                            ]
                        },
                        {
                            "nodeName": "set_point_position2",
                            "nodeType": "Geometry::Properties::set_point_position",
                            "metadata": [
                                {
                                    "metaName": "DisplayMode",
                                    "metaType": "string",
                                    "metaValue": "2"
                                },
                                {
                                    "metaName": "LayoutPos",
                                    "metaType": "string",
                                    "metaValue": "1998 -1538"
                                }
                            ]
                        },
                        {
                            "nodeName": "rotate_by_quaternion",
                            "nodeType": "Core::Math::rotate_by_quaternion",
                            "metadata": [
                                {
                                    "metaName": "DisplayMode",
                                    "metaType": "string",
                                    "metaValue": "2"
                                },
                                {
                                    "metaName": "LayoutPos",
                                    "metaType": "string",
                                    "metaValue": "468 -1598"
                                }
                            ]
                        }
                    ],
                    "connections": [
                        {
                            "source": "subtract.output",
                            "target": "add.first.output1"
                        },
                        {
                            "source": "sample_property1.sampled_data",
                            "target": "add.first.sampled_data"
                        },
                        {
                            "source": ".latticeBase",
                            "target": "get_closest_locations.geometry"
                        },
                        {
                            "source": "get_point_position.point_position",
                            "target": "get_closest_locations.positions"
                        },
                        {
                            "source": "get_closest_locations.locations",
                            "target": "sample_property.locations"
                        },
                        {
                            "source": "get_closest_locations.locations",
                            "target": "sample_property1.locations"
                        },
                        {
                            "source": ".geometryShape",
                            "target": "get_point_position.geometry"
                        },
                        {
                            "source": "get_point_position.point_position",
                            "target": "subtract.first.point_position"
                        },
                        {
                            "source": ".latticeBase",
                            "target": "sample_property.geometry"
                        },
                        {
                            "source": "sample_property.sampled_data",
                            "target": "subtract.first.sampled_data"
                        },
                        {
                            "source": ".latticeShape",
                            "target": "sample_property1.geometry"
                        },
                        {
                            "source": ".smoothIterations",
                            "target": "smooth_mesh_compound.smoothIterations"
                        },
                        {
                            "source": "add.output",
                            "target": "subtract1.first.output1"
                        },
                        {
                            "source": "get_point_position.point_position",
                            "target": "subtract1.first.point_position"
                        },
                        {
                            "source": ".geometryShape",
                            "target": "set_point_position1.geometry"
                        },
                        {
                            "source": "subtract1.output",
                            "target": "set_point_position1.positions"
                        },
                        {
                            "source": "set_point_position1.out_geometry",
                            "target": "smooth_mesh_compound.geometryShape"
                        },
                        {
                            "source": "smooth_mesh_compound.out_geometry",
                            "target": "get_point_position1.geometry"
                        },
                        {
                            "source": "get_point_position.point_position",
                            "target": "add1.first.point_position"
                        },
                        {
                            "source": "get_point_position1.point_position",
                            "target": "add1.first.point_position1"
                        },
                        {
                            "source": "add1.output",
                            "target": "set_point_position2.positions"
                        },
                        {
                            "source": ".geometryShape",
                            "target": "set_point_position2.geometry"
                        },
                        {
                            "source": "set_point_position2.out_geometry",
                            "target": ".out_geometry"
                        },
                        {
                            "source": "subtract.output",
                            "target": "rotate_by_quaternion.vector"
                        }
                    ],
                    "values": [
                        {
                            "valueName": "get_closest_locations.use_cutoff_distance",
                            "valueType": "bool",
                            "value": "true"
                        },
                        {
                            "valueName": "get_closest_locations.cutoff_distance",
                            "valueType": "float",
                            "value": "10f"
                        },
                        {
                            "valueName": "sample_property.default",
                            "valueType": "Math::float3",
                            "value": {
                                "x": "0f",
                                "y": "0f",
                                "z": "0f"
                            }
                        },
                        {
                            "valueName": "sample_property.property",
                            "valueType": "string",
                            "value": "point_position"
                        },
                        {
                            "valueName": "sample_property.method",
                            "valueType": "BifrostExp::Geometry::SampleMethod",
                            "value": "interpolated"
                        },
                        {
                            "valueName": "sample_property1.default",
                            "valueType": "Math::float3",
                            "value": {
                                "x": "0f",
                                "y": "0f",
                                "z": "0f"
                            }
                        },
                        {
                            "valueName": "sample_property1.property",
                            "valueType": "string",
                            "value": "point_position"
                        },
                        {
                            "valueName": "sample_property1.method",
                            "valueType": "BifrostExp::Geometry::SampleMethod",
                            "value": "interpolated"
                        }
                    ],
                    "reservedNodeNames": [
                        {
                            "name": "input"
                        },
                        {
                            "name": "output"
                        }
                    ]
                }
            ],
            "compoundNodes": [
                {
                    "nodeName": "lattice_compound",
                    "nodeType": "lattice_compound",
                    "metadata": [
                        {
                            "metaName": "DisplayMode",
                            "metaType": "string",
                            "metaValue": "2"
                        },
                        {
                            "metaName": "LayoutPos",
                            "metaType": "string",
                            "metaValue": "-767.392 -905.362"
                        }
                    ]
                }
            ],
            "connections": [
                {
                    "source": ".latticeBase",
                    "target": "lattice_compound.latticeBase"
                },
                {
                    "source": ".geometryShape",
                    "target": "lattice_compound.geometryShape"
                },
                {
                    "source": ".latticeShape",
                    "target": "lattice_compound.latticeShape"
                },
                {
                    "source": "lattice_compound.out_geometry",
                    "target": ".out_geometry"
                },
                {
                    "source": ".smoothIterations",
                    "target": "lattice_compound.smoothIterations"
                }
            ],
            "values": [
                {
                    "valueName": "lattice_compound.latticeBase",
                    "valueType": "Object",
                    "value": {}
                },
                {
                    "valueName": "lattice_compound.geometryShape",
                    "valueType": "Object",
                    "value": {}
                },
                {
                    "valueName": "lattice_compound.latticeShape",
                    "valueType": "Object",
                    "value": {}
                }
            ],
            "reservedNodeNames": [
                {
                    "name": "input"
                },
                {
                    "name": "output"
                }
            ]
        }
    ]
}
